{
  "id": 230,
  "title": "Kth Smallest Element in a BST",
  "difficulty": "Medium",
  "category": "Tree",
  "timeComplexity": "O(h+k)",
  "spaceComplexity": "O(h)",
  "description": "Cho BST root và k. Trả giá trị node nhỏ thứ k (1-indexed) trong thứ tự inorder tăng dần.",
  "examples": [
    { "input": "root = [3,1,4,null,2], k = 1", "output": "1" },
    { "input": "root = [5,3,6,2,4,null,null,1], k = 3", "output": "3" }
  ],
  "approach": "Inorder iterative: stack push left chain; pop, k--; k==0 return val; sang right.",
  "memoryTip": "Kth smallest BST = inorder stop at k — không cần sort cả tree.",
  "solutions": {
    "python": "class Solution:\n    def kthSmallest(self, root: Optional[TreeNode], k: int) -> int:\n        stack = []\n        cur = root\n        while cur or stack:\n            while cur:\n                stack.append(cur)\n                cur = cur.left\n            cur = stack.pop()\n            k -= 1\n            if k == 0:\n                return cur.val\n            cur = cur.right",
    "cpp": "class Solution {\npublic:\n    int kthSmallest(TreeNode* root, int k) {\n        stack<TreeNode*> st;\n        TreeNode* cur = root;\n        while (cur || !st.empty()) {\n            while (cur) { st.push(cur); cur = cur->left; }\n            cur = st.top(); st.pop();\n            if (--k == 0) return cur->val;\n            cur = cur->right;\n        }\n        return -1;\n    }\n};",
    "c": "int kthSmallest(struct TreeNode* root, int k) {\n    struct TreeNode* stack[1000];\n    int top = 0;\n    struct TreeNode* cur = root;\n    while (cur || top) {\n        while (cur) { stack[top++] = cur; cur = cur->left; }\n        cur = stack[--top];\n        if (--k == 0) return cur->val;\n        cur = cur->right;\n    }\n    return -1;\n}"
  },
  "analysis": {
    "correctness": "Inorder BST cho thứ tự tăng; dừng ở lần pop thứ k.",
    "edgeCases": ["k=1 → min", "Right-skew tree vẫn O(n)"],
    "pitfalls": ["DFS thu mảng O(n) space", "Quên push left trước pop"]
  },
  "tier": "done"
}
