{
  "id": 598,
  "title": "Range Addition II",
  "difficulty": "Easy",
  "category": "Array",
  "timeComplexity": "O(n)",
  "spaceComplexity": "O(1)",
  "description": "Ma trận m×n ban đầu toàn 0. Mỗi op [r,c] cộng 1 mọi ô (i,j) với 0≤i<r, 0≤j<c. Trả số ô có giá trị lớn nhất.",
  "examples": [
    {
      "input": "m=3, n=3, ops=[[2,2],[3,3]]",
      "output": "4"
    },
    {
      "input": "m=3, n=3, ops=[]",
      "output": "9"
    }
  ],
  "approach": "Mọi op cộng hình chữ nhật góc trên; max count = min(r)*min(c) over all ops (hoặc m*n nếu rỗng).",
  "memoryTip": "Range Addition II = answer is minRow * minCol across ops.",
  "solutions": {
    "python": "class Solution:\n    def maxCount(self, m: int, n: int, ops: List[List[int]]) -> int:\n        if not ops:\n            return m * n\n        mr = min(op[0] for op in ops)\n        mc = min(op[1] for op in ops)\n        return mr * mc",
    "cpp": "class Solution {\npublic:\n    int maxCount(int m, int n, vector<vector<int>>& ops) {\n        if (ops.empty()) return m * n;\n        int mr = m, mc = n;\n        for (auto& op : ops) { mr = min(mr, op[0]); mc = min(mc, op[1]); }\n        return mr * mc;\n    }\n};",
    "c": "/* min r min c product — xem C++ */"
  },
  "analysis": {
    "correctness": "Giao mọi hình chữ nhật op là [0,minR)×[0,minC); mọi ô đó nhận mọi op.",
    "edgeCases": [
      "ops rỗng → m*n",
      "Op nhỏ hơn ma trận"
    ],
    "pitfalls": [
      "Simulate matrix O(mn*ops)",
      "Max thay vì min trên ops"
    ]
  },
  "tier": "done"
}
