{
  "id": 627,
  "title": "Swap Sex of Employees",
  "difficulty": "Easy",
  "category": "Database",
  "timeComplexity": "O(n)",
  "spaceComplexity": "O(n)",
  "description": "Bảng Salary(id, name, sex, salary). Đổi sex f↔m, giữ name và salary.",
  "examples": [
    {
      "input": "sex=f",
      "output": "m"
    },
    {
      "input": "sex=m",
      "output": "f"
    }
  ],
  "approach": "UPDATE ... CASE sex WHEN 'f' THEN 'm' ELSE 'f' END (hoặc SELECT với CASE).",
  "memoryTip": "Swap sex = CASE flip f/m in SELECT or UPDATE.",
  "solutions": {
    "python": "# SQL\nUPDATE Salary\nSET sex = CASE\n  WHEN sex = 'f' THEN 'm'\n  ELSE 'f'\nEND;",
    "cpp": "// SQL\nUPDATE Salary\nSET sex = CASE\n  WHEN sex = 'f' THEN 'm'\n  ELSE 'f'\nEND;",
    "c": "const char query[] = \"UPDATE Salary\\nSET sex = CASE\\n  WHEN sex = 'f' THEN 'm'\\n  ELSE 'f'\\nEND;\";"
  },
  "analysis": {
    "correctness": "CASE đảo f/m cho mọi hàng.",
    "edgeCases": [
      "Chỉ một giới",
      "NULL sex"
    ],
    "pitfalls": [
      "Ghi đè name/salary",
      "Thiếu ELSE"
    ]
  },
  "tier": "done"
}
